tests/__init__.py
tests/test_acquistion_functions.py
tests/test_deep_surrogate_models.py
tests/test_optimizer.py
tests/test_searcher.py
tests/test_trial.py
tests/test_utils.py
tests/integrated_test/__init__.py
tests/integrated_test/test_mnist_opt_hyperparams.py
tfdbonas/__init__.py
tfdbonas/acquistion_functions.py
tfdbonas/deep_surrogate_models.py
tfdbonas/layers.py
tfdbonas/optimizer.py
tfdbonas/searcher.py
tfdbonas/trial.py
tfdbonas/utils.py
tfdbonas-0.1.0.dist-info/METADATA
tfdbonas-0.1.0.dist-info/WHEEL
tfdbonas-0.1.0.dist-info/top_level.txt
tfdbonas-0.1.0.dist-info/RECORD
