Metadata-Version: 2.1
Name: tfdbonas
Version: 0.1.0
Summary: Tensorflow Deep Bayes Optimization for Neural Network Architecture Search (tfDBONAS)
Home-page: https://github.com/0h-n0/tfdbonas
Author: Koji Ono
Author-email: kbu94982@gmail.com
License: UNKNOWN
Platform: UNKNOWN
Classifier: Programming Language :: Python :: 3.6
Classifier: Programming Language :: Python :: 3.7
Requires-Python: >3.5
Provides-Extra: docs
Requires-Dist: sphinx (>=1.4) ; extra == 'docs'
Requires-Dist: sphinx-rtd-theme ; extra == 'docs'
